main1.py
runner.py
safe_runner.py
mainx-1.0.dist-info/licenses/LICENSE.txt
mainx-1.0.dist-info/METADATA
mainx-1.0.dist-info/WHEEL
mainx-1.0.dist-info/entry_points.txt
mainx-1.0.dist-info/top_level.txt
mainx-1.0.dist-info/RECORD
