Metadata-Version: 2.4
Name: mainx
Version: 1.0
Summary: Educational bug simulation tool with system, network, encryption, and Discord support
Author: Your Name
License: MIT
Classifier: Programming Language :: Python :: 3
Classifier: License :: OSI Approved :: MIT License
Classifier: Operating System :: OS Independent
Requires-Python: >=3.6
License-File: LICENSE.txt
Requires-Dist: requests
Requires-Dist: discord.py>=2.0.0
Requires-Dist: pycryptodome
Requires-Dist: cryptography
Requires-Dist: pywin32; platform_system == "Windows"
Dynamic: author
Dynamic: classifier
Dynamic: description
Dynamic: description-content-type
Dynamic: license
Dynamic: license-file
Dynamic: requires-dist
Dynamic: requires-python
Dynamic: summary
